<?xml version="1.0" encoding="utf-8" ?>
<dwsync>
<file name="index.php" server="C:/AppServ/MyWebSite/" local="129169971460000000" remote="129169971460000000" Dst="-1" />
<file name="search.php" server="C:/AppServ/MyWebSite/" local="129170847294375000" remote="129170847290000000" Dst="-1" />
<file name="category_product.php" server="C:/AppServ/MyWebSite/" local="129169975093125000" remote="129169975090000000" Dst="-1" />
<file name="show_detail.php" server="C:/AppServ/MyWebSite/" local="129154449643281250" remote="129154449640000000" Dst="-1" />
<file name="category_product2.php" server="C:/AppServ/MyWebSite/" local="129170833037031250" remote="129170833030000000" Dst="-1" />
<file name="product_item.php" server="C:/AppServ/MyWebSite/" local="129169974324843750" remote="129169974320000000" Dst="-1" />
<file name="discuss.php" server="C:/AppServ/MyWebSite/" local="129170833484218750" remote="129170833480000000" Dst="-1" />
<file name="discuss_detail.php" server="C:/AppServ/MyWebSite/" local="129153455996875000" remote="129153455990000000" Dst="-1" />
<file name="notifications_friend.php" server="C:/AppServ/MyWebSite/" local="129154650971406250" remote="129154650970000000" Dst="-1" />
<file name="profile.php" server="C:/AppServ/MyWebSite/" local="129157366077031250" remote="129157366070000000" Dst="-1" />
<file name="profile_product.php" server="C:/AppServ/MyWebSite/" local="129156379653906250" remote="129156379650000000" Dst="-1" />
<file name="profile_show.php" server="C:/AppServ/MyWebSite/" local="129157366310468750" remote="129157366310000000" Dst="-1" />
<file name="profile_friend.php" server="C:/AppServ/MyWebSite/" local="129169974012812500" remote="129169974010000000" Dst="-1" />
<file name="profile_talk.php" server="C:/AppServ/MyWebSite/" local="129164143966718750" remote="129164143960000000" Dst="-1" />
<file name="register.php" server="C:/AppServ/MyWebSite/" local="129161421150156250" remote="129161421150000000" Dst="-1" />
<file name="register2.php" server="C:/AppServ/MyWebSite/" local="129158107386406250" remote="129158107380000000" Dst="-1" />
<file name="register3.php" server="C:/AppServ/MyWebSite/" local="129158131459687500" remote="129158131450000000" Dst="-1" />
<file name="car.php" server="C:/AppServ/MyWebSite/" local="129161592544687500" remote="129161592540000000" Dst="-1" />
<file name="car2.php" server="C:/AppServ/MyWebSite/" local="129167301248437500" remote="129167301240000000" Dst="-1" />
<file name="car3.php" server="C:/AppServ/MyWebSite/" local="129161593088125000" remote="129161593080000000" Dst="-1" />
<file name="order.php" server="C:/AppServ/MyWebSite/" local="129162022865937500" remote="129162022860000000" Dst="-1" />
<file name="car4.php" server="C:/AppServ/MyWebSite/" local="129161593868281250" remote="129161593860000000" Dst="-1" />
<file name="user.php" server="C:/AppServ/MyWebSite/" local="129162969912031250" remote="129162969910000000" Dst="-1" />
<file name="user_show.php" server="C:/AppServ/MyWebSite/" local="129178425815468750" remote="129178425810000000" Dst="-1" />
<file name="user_talk.php" server="C:/AppServ/MyWebSite/" local="129164815012187500" remote="129164815010000000" Dst="-1" />
<file name="system_msg.php" server="C:/AppServ/MyWebSite/" local="129165714501406250" remote="129165714500000000" Dst="-1" />
<file name="user_friend.php" server="C:/AppServ/MyWebSite/" local="129167665951250000" remote="129167665950000000" Dst="-1" />
<file name="top.php" server="C:/AppServ/MyWebSite/" local="129161975182500000" remote="129161975180000000" Dst="-1" />
<file name="account.php" server="C:/AppServ/MyWebSite/" local="129167359967187500" remote="129167359960000000" Dst="-1" />
<file name="order2.php" server="C:/AppServ/MyWebSite/" local="129163981008437500" remote="129163981000000000" Dst="-1" />
<file name="invite.php" server="C:/AppServ/MyWebSite/" local="129167670170312500" remote="129167670170000000" Dst="-1" />
<file name="store.php" server="C:/AppServ/MyWebSite/" local="129175961116718750" remote="129175961110000000" Dst="-1" />
<file name="store_pass.php" server="C:/AppServ/MyWebSite/" local="129176308814843750" remote="129176308810000000" Dst="-1" />
<file name="store_intro.php" server="C:/AppServ/MyWebSite/" local="129175969070468750" remote="129175969070000000" Dst="-1" />
<file name="store_help.php" server="C:/AppServ/MyWebSite/" local="129176154289062500" remote="129176154280000000" Dst="-1" />
<file name="store_customer.php" server="C:/AppServ/MyWebSite/" local="129176257534062500" remote="129176257530000000" Dst="-1" />
<file name="index.php" server="C:/AppServ/www/" local="129169971460000000" remote="129169971460000000" Dst="0" />
<file name="top.php" server="C:/AppServ/www/" local="129168279240000000" remote="129168279240000000" Dst="0" />
<file name="new.php" server="C:/AppServ/www/" local="130427122814059886" remote="130427122810000000" Dst="0" />
</dwsync>